MANIFEST.in
README.md
setup.py
bin/CreateFlowtable.py
bin/CreateFlowtableMultiple.py
bin/CreateGRASSLocationFromDEM.py
bin/CreateWorldfile.py
bin/CreateWorldfileMultiple.py
bin/DelineateWatershed.py
bin/GIConverter.py
bin/GenerateBaseStationMap.py
bin/GenerateCustomSoilDefinitions.py
bin/GenerateLandcoverMaps.py
bin/GeneratePatchMap.py
bin/GenerateSoilTextureMap.py
bin/GenerateWorldTemplate.py
bin/ImportClimateData.py
bin/ImportRHESSysSource.py
bin/ImportRasterMapIntoGRASS.py
bin/PatchToCumulativeMap.py
bin/PatchToCumulativeValues.py
bin/PatchToMap.py
bin/PatchToMovie.py
bin/PatchZonalStats.py
bin/PatchZonalStatsNormalize.py
bin/RHESSysPlot.py
bin/RHESSysPlotMassbalance.py
bin/RegisterCustomSoilReclassRules.py
bin/RegisterLandcoverReclassRules.py
bin/RunLAIRead.py
bin/RunLAIReadMultiple.py
bin/RunModel.py
etc/NLCD2006/impervious.rule
etc/NLCD2006/lai-recode.rule
etc/NLCD2006/landuse.rule
etc/NLCD2006/road.rule
etc/NLCD2006/stratum.rule
etc/NLCD2011/impervious.rule
etc/NLCD2011/lai-recode.rule
etc/NLCD2011/landuse.rule
etc/NLCD2011/road.rule
etc/NLCD2011/stratum.rule
etc/r.soils.texture/FAO.dat
etc/r.soils.texture/USDA.dat
etc/r.soils.texture/isss.dat
rhessysworkflows/__init__.py
rhessysworkflows/climateio.py
rhessysworkflows/compat.py
rhessysworkflows/context.py
rhessysworkflows/ginotebook.py
rhessysworkflows/metadata.py
rhessysworkflows/rhessys.py
rhessysworkflows/worldfileio.py
rhessysworkflows.egg-info/PKG-INFO
rhessysworkflows.egg-info/SOURCES.txt
rhessysworkflows.egg-info/dependency_links.txt
rhessysworkflows.egg-info/not-zip-safe
rhessysworkflows.egg-info/requires.txt
rhessysworkflows.egg-info/top_level.txt
rhessysworkflows/command/__init__.py
rhessysworkflows/command/base.py
rhessysworkflows/command/exceptions.py
rhessysworkflows/command/flowtable.py
rhessysworkflows/command/giconverter.py
rhessysworkflows/command/modelrun.py
rhessysworkflows/command/worldfile.py
rhessysworkflows/tests/__init__.py
rhessysworkflows/tests/test_metadata.py