Metadata-Version: 1.1
Name: rhessysworkflows
Version: 1.34
Summary: Libraries and command-line scripts for performing RHESSys data preparation workflows.
Home-page: https://github.com/selimnairb/RHESSysWorkflows
Author: Brian Miles
Author-email: brian_miles@unc.edu
License: BSD
Platform: UNKNOWN
Classifier: Development Status :: 5 - Production/Stable
Classifier: Environment :: Console
Classifier: Intended Audience :: Science/Research
Classifier: License :: OSI Approved :: BSD License
Classifier: Natural Language :: English
Classifier: Operating System :: Unix
Classifier: Topic :: Scientific/Engineering :: GIS
